{
  "creator": "Yosys 0.53+3 (git sha1 6378ba10e, g++ 13.3.0-6ubuntu2~24.04 -fPIC -O3)",
  "modules": {
    "mux_4_1": {
      "attributes": {
        "top": "00000000000000000000000000000001",
        "src": "mux_4_1.v:1.1-24.10"
      },
      "ports": {
        "i0": {
          "direction": "input",
          "bits": [ 2 ]
        },
        "i1": {
          "direction": "input",
          "bits": [ 3 ]
        },
        "i2": {
          "direction": "input",
          "bits": [ 4 ]
        },
        "i3": {
          "direction": "input",
          "bits": [ 5 ]
        },
        "sel": {
          "direction": "input",
          "bits": [ 6, 7 ]
        },
        "y": {
          "direction": "output",
          "bits": [ 8 ]
        }
      },
      "cells": {
        "$abc$140$auto$blifparse.cc:396:parse_blif$141": {
          "hide_name": 1,
          "type": "$_NOR_",
          "parameters": {
          },
          "attributes": {
          },
          "port_directions": {
            "A": "input",
            "B": "input",
            "Y": "output"
          },
          "connections": {
            "A": [ 6 ],
            "B": [ 7 ],
            "Y": [ 9 ]
          }
        },
        "$abc$140$auto$blifparse.cc:396:parse_blif$142": {
          "hide_name": 1,
          "type": "$_NAND_",
          "parameters": {
          },
          "attributes": {
          },
          "port_directions": {
            "A": "input",
            "B": "input",
            "Y": "output"
          },
          "connections": {
            "A": [ 6 ],
            "B": [ 7 ],
            "Y": [ 10 ]
          }
        },
        "$abc$140$auto$blifparse.cc:396:parse_blif$143": {
          "hide_name": 1,
          "type": "$_ANDNOT_",
          "parameters": {
          },
          "attributes": {
          },
          "port_directions": {
            "A": "input",
            "B": "input",
            "Y": "output"
          },
          "connections": {
            "A": [ 5 ],
            "B": [ 10 ],
            "Y": [ 11 ]
          }
        },
        "$abc$140$auto$blifparse.cc:396:parse_blif$144": {
          "hide_name": 1,
          "type": "$_ORNOT_",
          "parameters": {
          },
          "attributes": {
          },
          "port_directions": {
            "A": "input",
            "B": "input",
            "Y": "output"
          },
          "connections": {
            "A": [ 6 ],
            "B": [ 7 ],
            "Y": [ 12 ]
          }
        },
        "$abc$140$auto$blifparse.cc:396:parse_blif$145": {
          "hide_name": 1,
          "type": "$_ANDNOT_",
          "parameters": {
          },
          "attributes": {
          },
          "port_directions": {
            "A": "input",
            "B": "input",
            "Y": "output"
          },
          "connections": {
            "A": [ 4 ],
            "B": [ 12 ],
            "Y": [ 13 ]
          }
        },
        "$abc$140$auto$blifparse.cc:396:parse_blif$146": {
          "hide_name": 1,
          "type": "$_OR_",
          "parameters": {
          },
          "attributes": {
          },
          "port_directions": {
            "A": "input",
            "B": "input",
            "Y": "output"
          },
          "connections": {
            "A": [ 13 ],
            "B": [ 11 ],
            "Y": [ 14 ]
          }
        },
        "$abc$140$auto$blifparse.cc:396:parse_blif$147": {
          "hide_name": 1,
          "type": "$_ORNOT_",
          "parameters": {
          },
          "attributes": {
          },
          "port_directions": {
            "A": "input",
            "B": "input",
            "Y": "output"
          },
          "connections": {
            "A": [ 7 ],
            "B": [ 6 ],
            "Y": [ 15 ]
          }
        },
        "$abc$140$auto$blifparse.cc:396:parse_blif$148": {
          "hide_name": 1,
          "type": "$_ANDNOT_",
          "parameters": {
          },
          "attributes": {
          },
          "port_directions": {
            "A": "input",
            "B": "input",
            "Y": "output"
          },
          "connections": {
            "A": [ 3 ],
            "B": [ 15 ],
            "Y": [ 16 ]
          }
        },
        "$abc$140$auto$blifparse.cc:396:parse_blif$149": {
          "hide_name": 1,
          "type": "$_OR_",
          "parameters": {
          },
          "attributes": {
          },
          "port_directions": {
            "A": "input",
            "B": "input",
            "Y": "output"
          },
          "connections": {
            "A": [ 16 ],
            "B": [ 14 ],
            "Y": [ 17 ]
          }
        },
        "$abc$140$auto$blifparse.cc:396:parse_blif$150": {
          "hide_name": 1,
          "type": "$_MUX_",
          "parameters": {
          },
          "attributes": {
          },
          "port_directions": {
            "A": "input",
            "B": "input",
            "S": "input",
            "Y": "output"
          },
          "connections": {
            "A": [ 17 ],
            "B": [ 2 ],
            "S": [ 9 ],
            "Y": [ 8 ]
          }
        }
      },
      "netnames": {
        "$abc$140$new_n10": {
          "hide_name": 1,
          "bits": [ 11 ],
          "attributes": {
          }
        },
        "$abc$140$new_n11": {
          "hide_name": 1,
          "bits": [ 12 ],
          "attributes": {
          }
        },
        "$abc$140$new_n12": {
          "hide_name": 1,
          "bits": [ 13 ],
          "attributes": {
          }
        },
        "$abc$140$new_n13": {
          "hide_name": 1,
          "bits": [ 14 ],
          "attributes": {
          }
        },
        "$abc$140$new_n14": {
          "hide_name": 1,
          "bits": [ 15 ],
          "attributes": {
          }
        },
        "$abc$140$new_n15": {
          "hide_name": 1,
          "bits": [ 16 ],
          "attributes": {
          }
        },
        "$abc$140$new_n16": {
          "hide_name": 1,
          "bits": [ 17 ],
          "attributes": {
          }
        },
        "$abc$140$new_n8": {
          "hide_name": 1,
          "bits": [ 9 ],
          "attributes": {
          }
        },
        "$abc$140$new_n9": {
          "hide_name": 1,
          "bits": [ 10 ],
          "attributes": {
          }
        },
        "i0": {
          "hide_name": 0,
          "bits": [ 2 ],
          "attributes": {
            "src": "mux_4_1.v:3.12-3.14"
          }
        },
        "i1": {
          "hide_name": 0,
          "bits": [ 3 ],
          "attributes": {
            "src": "mux_4_1.v:4.12-4.14"
          }
        },
        "i2": {
          "hide_name": 0,
          "bits": [ 4 ],
          "attributes": {
            "src": "mux_4_1.v:5.12-5.14"
          }
        },
        "i3": {
          "hide_name": 0,
          "bits": [ 5 ],
          "attributes": {
            "src": "mux_4_1.v:6.12-6.14"
          }
        },
        "sel": {
          "hide_name": 0,
          "bits": [ 6, 7 ],
          "attributes": {
            "src": "mux_4_1.v:7.18-7.21"
          }
        },
        "y": {
          "hide_name": 0,
          "bits": [ 8 ],
          "attributes": {
            "src": "mux_4_1.v:8.12-8.13"
          }
        }
      }
    }
  }
}
